entropy-mdlp/__init__.py
entropy-mdlp/mdlp.py
entropymdlp/__init__.py
entropymdlp/mdlp.py
entropymdlp-0.1.dist-info/DESCRIPTION.rst
entropymdlp-0.1.dist-info/METADATA
entropymdlp-0.1.dist-info/RECORD
entropymdlp-0.1.dist-info/WHEEL
entropymdlp-0.1.dist-info/metadata.json
entropymdlp-0.1.dist-info/top_level.txt
mdlp/__init__.py
mdlp/mdlp.py
